BrosHelp/BrosHelp.py
BrosHelp/Start.py
BrosHelp/__init__.py
BrosHelp/__main__.py
BrosHelp/wxpy/__init__.py
BrosHelp/wxpy/__main__.py
BrosHelp/wxpy/exceptions.py
BrosHelp/wxpy/api/__init__.py
BrosHelp/wxpy/api/bot.py
BrosHelp/wxpy/api/chats/__init__.py
BrosHelp/wxpy/api/chats/chat.py
BrosHelp/wxpy/api/chats/chats.py
BrosHelp/wxpy/api/chats/friend.py
BrosHelp/wxpy/api/chats/group.py
BrosHelp/wxpy/api/chats/groups.py
BrosHelp/wxpy/api/chats/member.py
BrosHelp/wxpy/api/chats/mp.py
BrosHelp/wxpy/api/chats/user.py
BrosHelp/wxpy/api/messages/__init__.py
BrosHelp/wxpy/api/messages/message.py
BrosHelp/wxpy/api/messages/message_config.py
BrosHelp/wxpy/api/messages/message_configs.py
BrosHelp/wxpy/api/messages/messages.py
BrosHelp/wxpy/ext/__init__.py
BrosHelp/wxpy/ext/logging_with_wechat.py
BrosHelp/wxpy/ext/tuling.py
BrosHelp/wxpy/utils/__init__.py
BrosHelp/wxpy/utils/console.py
BrosHelp/wxpy/utils/misc.py
BrosHelp/wxpy/utils/tools.py
BrosHelp-0.1.17.dist-info/DESCRIPTION.rst
BrosHelp-0.1.17.dist-info/METADATA
BrosHelp-0.1.17.dist-info/RECORD
BrosHelp-0.1.17.dist-info/WHEEL
BrosHelp-0.1.17.dist-info/entry_points.txt
BrosHelp-0.1.17.dist-info/metadata.json
BrosHelp-0.1.17.dist-info/top_level.txt
