Metadata-Version: 2.0
Name: BrosHelp
Version: 0.1.17
Summary: BrosHelp Bot
Home-page: https://github.com/KayShenA/PythonProjects
Author: Kay
Author-email: skyluckyrrb@126.com
License: MIT
Platform: any
Requires-Dist: itchat (==1.2.32)
Requires-Dist: requests
